mwdrive/__init__.py
mwdrive/api_client.py
mwdrive/config.py
mwdrive/crypto.py
mwdrive/database.py
mwdrive/dfu.py
mwdrive/enums.py
mwdrive/firmware.py
mwdrive/hw_version.py
mwdrive/legacy.py
mwdrive/legacy_config.py
mwdrive/mtool.py
mwdrive/release_api.py
mwdrive/rich_text.py
mwdrive/shell.py
mwdrive/utils.py
mwdrive/version.py
mwdrive/data/brakeRs.json
mwdrive/data/drvs.json
mwdrive/data/encoders.json
mwdrive/data/motors.json
mwdrive/data/odrive-micro-x1.json
mwdrive/data/odrive-micro-x3.json
mwdrive/data/odrive-s1-x4.json
mwdrive/data/odrive-v4.4.json
mwdrive/data/schema-brakeR.json
mwdrive/data/schema-drv.json
mwdrive/data/schema-encoders.json
mwdrive/data/schema-motors.json
mwdrive/data/schema-odrive.json
mwdrive/data/schema.json
mwdrive/dfuse/DfuDevice.py
mwdrive/dfuse/__init__.py
mwdrive/pyfibre/fibre/__init__.py
mwdrive/pyfibre/fibre/libfibre-linux-aarch64.so
mwdrive/pyfibre/fibre/libfibre-linux-amd64.so
mwdrive/pyfibre/fibre/libfibre-linux-armhf.so
mwdrive/pyfibre/fibre/libfibre-macos-arm.dylib
mwdrive/pyfibre/fibre/libfibre-macos-x86.dylib
mwdrive/pyfibre/fibre/libfibre-windows-amd64.dll
mwdrive/pyfibre/fibre/libfibre.py
mwdrive/pyfibre/fibre/libwinpthread-1.dll
mwdrive/pyfibre/fibre/shell.py
mwdrive/pyfibre/fibre/utils.py
mwdrive/pyfibre/fibre/__pycache__/__init__.cpython-312.pyc
mwdrive/pyfibre/fibre/__pycache__/libfibre.cpython-312.pyc
mwdrive/pyfibre/fibre/__pycache__/shell.cpython-312.pyc
mwdrive/pyfibre/fibre/__pycache__/utils.cpython-312.pyc
mwdrive-1.0.14.data/scripts/mtool
mwdrive-1.0.14.data/scripts/mtool.bat
mwdrive-1.0.14.dist-info/licenses/LICENSE
mwdrive-1.0.14.dist-info/METADATA
mwdrive-1.0.14.dist-info/WHEEL
mwdrive-1.0.14.dist-info/top_level.txt
mwdrive-1.0.14.dist-info/RECORD
