Metadata-Version: 2.4
Name: mwdrive
Version: 1.0.14
Summary: Motor Driver Control Library for products from CyberBeast
Author: CyberBeast
Classifier: Programming Language :: Python :: 3
License-File: LICENSE
Dynamic: author
Dynamic: classifier
Dynamic: description
Dynamic: description-content-type
Dynamic: license-file
Dynamic: summary
